turing/__init__.py
turing/core/__init__.py
turing/core/client/__init__.py
turing/core/client/client.py
turing/core/errors.py
turing/core/models/__init__.py
turing/core/models/grading_criteria.py
turing/core/models/objective.py
turing/core/models/rubric.py
turing/core/models/short_answer.py
turing/tests/__init__.py
turing/tests/client/__init__.py
turing/tests/client/test_client.py
turing/tests/models/__init__.py
turing/tests/models/test_criteria.py
turing/tests/models/test_objective.py
turing/tests/models/test_question.py
turing/tests/models/test_rubric.py
turing_ai-0.0.1.dist-info/LICENSE
turing_ai-0.0.1.dist-info/METADATA
turing_ai-0.0.1.dist-info/WHEEL
turing_ai-0.0.1.dist-info/RECORD
